qq_chat_history/__init__.py
qq_chat_history/body.py
qq_chat_history/cli.py
qq_chat_history/message.py
qq_chat_history/py.typed
qq_chat_history-1.1.7.dist-info/entry_points.txt
qq_chat_history-1.1.7.dist-info/LICENSE
qq_chat_history-1.1.7.dist-info/METADATA
qq_chat_history-1.1.7.dist-info/WHEEL
qq_chat_history-1.1.7.dist-info/RECORD
