Metadata-Version: 2.1
Name: qq-chat-history
Version: 1.1.7
Summary: A tool to extract QQ chat history.
Home-page: https://github.com/hikariyo/qq-chat-history
License: MIT
Author: hikariyo
Author-email: hikariyo1@outlook.com
Requires-Python: >=3.9,<4.0
Classifier: License :: OSI Approved :: MIT License
Classifier: Programming Language :: Python :: 3
Classifier: Programming Language :: Python :: 3.9
Classifier: Programming Language :: Python :: 3.10
Classifier: Programming Language :: Python :: 3.11
Requires-Dist: click (>=8.1.3,<9.0.0)
Requires-Dist: pyyaml (>=6.0,<7.0)
Requires-Dist: ujson (>=5.7.0,<6.0.0)
Project-URL: Repository, https://github.com/hikariyo/qq-chat-history
